{"uuid":"962538e49cb1e0a98f9146ddc9eec236b8a43586","bioAsHtml":"<p>Initialement développeur spécialisé dans les technologies Java / JAVA EE. Tout au long de mes diverses missions, j&#x27;a eu l&#x27;occassion d&#x27;avoir une expérience diversifiée aussi bien côté DEV qu&#x27;Infra.\nPassionné par l&#x27;industrialisation, je trouve toujours quelque chose à automatiser. J&#x27; ai un role parfait dans le DEVOPS.</p>\n","acceptedTalks":[{"talkType":"Conference","track":"Web, JS, HTML5 et UX","links":[{"href":"http://cfp.devoxx.fr/api/conferences/DevoxxFR2018/talks/UMQ-0422","rel":"http://cfp.devoxx.fr/api/profile/talk","title":"More details about this talk"},{"href":"http://cfp.devoxx.fr/api/conferences/DevoxxFR2018/speakers/701c8a3ef546d676193c33948a54fb65dceb3105","rel":"http://cfp.devoxx.fr/api/profile/speaker","title":"Sébastien LECACHEUR"},{"href":"http://cfp.devoxx.fr/api/conferences/DevoxxFR2018/speakers/962538e49cb1e0a98f9146ddc9eec236b8a43586","rel":"http://cfp.devoxx.fr/api/profile/speaker","title":"Grégory Bloquel"}],"id":"UMQ-0422","title":"Swagger 2 est mort, vive OpenAPI 3"}],"company":"Adventiel","bio":"Initialement développeur spécialisé dans les technologies Java / JAVA EE. Tout au long de mes diverses missions, j'a eu l'occassion d'avoir une expérience diversifiée aussi bien côté DEV qu'Infra. \r\nPassionné par l'industrialisation, je trouve toujours quelque chose à automatiser. J' ai un role parfait dans le DEVOPS.","lastName":"Bloquel","firstName":"Grégory","blog":null,"avatarURL":"http://gravatar.com/avatar/df747935bec069aee97b9fcd124fc7c3","twitter":"@gbloquel","lang":"fr"}